setup.cfg
setup.py
linode_api3/__init__.py
linode_api3/api.py
linode_api3.egg-info/PKG-INFO
linode_api3.egg-info/SOURCES.txt
linode_api3.egg-info/dependency_links.txt
linode_api3.egg-info/requires.txt
linode_api3.egg-info/top_level.txt